pytest_order/__init__.py
pytest_order/item.py
pytest_order/plugin.py
pytest_order/settings.py
pytest_order/sorter.py
pytest_order-1.3.0.dist-info/LICENSE
pytest_order-1.3.0.dist-info/METADATA
pytest_order-1.3.0.dist-info/WHEEL
pytest_order-1.3.0.dist-info/entry_points.txt
pytest_order-1.3.0.dist-info/top_level.txt
pytest_order-1.3.0.dist-info/RECORD
